setup.py
pilabs2/__init__.py
pilabs2/example.py
pilabs2/main.py
pilabs2.egg-info/PKG-INFO
pilabs2.egg-info/SOURCES.txt
pilabs2.egg-info/dependency_links.txt
pilabs2.egg-info/top_level.txt