Metadata-Version: 1.0
Name: pilabs2
Version: 1.0.0
Summary: A python module by a maker v0.0.1(fixed bugs)
Home-page: UNKNOWN
Author: A Maker in USA
Author-email: sunnyoc123@outlook.com
License: UNKNOWN
Platform: UNKNOWN
